moat/modbus/__init__.py
moat/modbus/__main__.py
moat/modbus/_compat.py
moat/modbus/_main.py
moat/modbus/client.py
moat/modbus/server.py
moat/modbus/typemap.py
moat/modbus/types.py
moat/modbus/dev/__init__.py
moat/modbus/dev/_main.py
moat/modbus/dev/device.py
moat/modbus/dev/link.py
moat/modbus/dev/poll.py
moat/modbus/dev/server.py
moat_modbus-0.8.11.dist-info/licenses/LICENSE.txt
moat_modbus-0.8.11.dist-info/METADATA
moat_modbus-0.8.11.dist-info/WHEEL
moat_modbus-0.8.11.dist-info/top_level.txt
moat_modbus-0.8.11.dist-info/RECORD
