Metadata-Version: 2.4
Name: moat-modbus
Version: 0.8.11
Summary: Modular async modbus client and server
Author-email: Matthias Urlichs <matthias@urlichs.de>
Project-URL: homepage, https://m-o-a-t.org
Project-URL: repository, https://github.com/M-o-a-T/moat
Keywords: MoaT
Classifier: Intended Audience :: Developers
Classifier: Programming Language :: Python :: 3
Classifier: Framework :: AsyncIO
Classifier: Framework :: Trio
Classifier: Framework :: AnyIO
Classifier: Development Status :: 4 - Beta
Requires-Python: >=3.8
License-File: LICENSE.txt
Requires-Dist: anyio~=4.2
Requires-Dist: pymodbus~=3.6.0
Requires-Dist: anyio-serial
Requires-Dist: moat-util~=0.62.2
Requires-Dist: asyncscope~=0.8.3
Requires-Dist: pymodbus~=3.8
Requires-Dist: moat-lib-run~=0.1.1
Dynamic: license-file
